geometric_sampling/__init__.py
geometric_sampling/design.py
geometric_sampling/red_black_tree.py
geometric_sampling/structs.py
geometric_sampling/type.py
geometric_sampling/clustering/__init__.py
geometric_sampling/clustering/agg.py
geometric_sampling/clustering/aggregate_balancing_kmeans.py
geometric_sampling/clustering/soft_balanced_kmeans.py
geometric_sampling/criteria/__init__.py
geometric_sampling/criteria/criteria.py
geometric_sampling/criteria/var_nht.py
geometric_sampling/measure/__init__.py
geometric_sampling/measure/density.py
geometric_sampling/method/__init__.py
geometric_sampling/method/kmeans_spatial_sampling.py
geometric_sampling/method/population.py
geometric_sampling/random/__init__.py
geometric_sampling/random/generator.py
geometric_sampling/search/__init__.py
geometric_sampling/search/astar.py
geometric_sampling-0.4.3.dist-info/METADATA
geometric_sampling-0.4.3.dist-info/WHEEL
geometric_sampling-0.4.3.dist-info/licenses/LICENSE
geometric_sampling-0.4.3.dist-info/RECORD
