Metadata-Version: 2.4
Name: geometric-sampling
Version: 0.4.3
Summary: Python package for Geometric Sampling Method
Author-email: Bardia Panahbehagh <bardia.panah@gmail.com>, Mehdi Mohebbi <mehdi.mohebbi23@gmail.com>, AmirMohammad HosseiniNasab <awmirhn@gmail.com>, Mehdi Hosseini Moghadam <m.h.moghadam1996@gmail.com>
License-File: LICENSE
Requires-Python: >=3.10
Requires-Dist: matplotlib>=3.9.2
Requires-Dist: numpy>=2.1.2
Requires-Dist: scikit-learn>=1.6.1
Requires-Dist: scipy>=1.15.1
